{
  "bg": 159, 
  "temp": "absolute", 
  "snoozeBG": 156, 
  "timestamp": "2016-08-20T23:27:23.823526", 
  "missing": [
    "duration", 
    "rate"
  ], 
  "reason": "Eventual BG 147>=130, temp 1.175 >~ req 1.205U/hr", 
  "eventualBG": 147, 
  "error": "missing required input fields", 
  "input": {
    "reason": "Eventual BG 147>=130, temp 1.175 >~ req 1.205U/hr", 
    "bg": 159, 
    "eventualBG": 147, 
    "temp": "absolute", 
    "snoozeBG": 156, 
    "mealAssist": "Off: Carbs: undefined Boluses: undefined ISF: 80, Target: 130 Deviation: 12 BGI: -0.16", 
    "tick": "+4"
  }, 
  "mealAssist": "Off: Carbs: undefined Boluses: undefined ISF: 80, Target: 130 Deviation: 12 BGI: -0.16", 
  "tick": "+4"
}