{
  "device": "openaps://openaps-lp", 
  "pump": {
    "battery": {
      "status": "normal", 
      "voltage": 1.23
    }, 
    "status": {
      "status": "normal", 
      "timestamp": "2016-08-22T11:16:08.000Z", 
      "bolusing": false, 
      "suspended": false
    }, 
    "reservoir": 65.25, 
    "clock": "2016-08-22T04:14:56"
  }, 
  "openaps": {
    "suggested": {
      "bg": 285, 
      "temp": "absolute", 
      "snoozeBG": 249, 
      "timestamp": "2016-08-22T11:17:11.000Z", 
      "reason": "Eventual BG 120<130, bolus snooze: eventual BG range 120-249, temp 1.95 ~ req 1.95U/hr", 
      "eventualBG": 120, 
      "mealAssist": "Off: Carbs: undefined Boluses: undefined ISF: 80, Target: 130 Deviation: 14 BGI: -6.56", 
      "tick": -2
    }, 
    "iob": {
      "netbasalinsulin": -0.8, 
      "timestamp": "2016-08-22T11:16:59.000Z", 
      "activity": 0.0164, 
      "basaliob": 0.255, 
      "hightempinsulin": 0.9, 
      "bolussnooze": 1.072, 
      "iob": 2.239
    }, 
    "enacted": {
      "bg": 285, 
      "temp": "absolute", 
      "missing": [
        "duration", 
        "rate"
      ], 
      "timestamp": "2016-08-22T11:17:24.000Z", 
      "snoozeBG": 249, 
      "reason": "Eventual BG 120<130, bolus snooze: eventual BG range 120-249, temp 1.95 ~ req 1.95U/hr", 
      "eventualBG": 120, 
      "error": "missing required input fields", 
      "input": {
        "bg": 285, 
        "temp": "absolute", 
        "snoozeBG": 249, 
        "reason": "Eventual BG 120<130, bolus snooze: eventual BG range 120-249, temp 1.95 ~ req 1.95U/hr", 
        "eventualBG": 120, 
        "mealAssist": "Off: Carbs: undefined Boluses: undefined ISF: 80, Target: 130 Deviation: 14 BGI: -6.56", 
        "tick": -2
      }, 
      "mealAssist": "Off: Carbs: undefined Boluses: undefined ISF: 80, Target: 130 Deviation: 14 BGI: -6.56", 
      "tick": -2
    }
  }
}